mets_tools/__init__.py
mets_tools/_modidx.py
mets_tools/core.py
mets_tools-0.0.1.dist-info/LICENSE
mets_tools-0.0.1.dist-info/METADATA
mets_tools-0.0.1.dist-info/WHEEL
mets_tools-0.0.1.dist-info/entry_points.txt
mets_tools-0.0.1.dist-info/top_level.txt
mets_tools-0.0.1.dist-info/RECORD
